inventree_zapier/ZapierPlugin.py
inventree_zapier/__init__.py
inventree_zapier/models.py
inventree_zapier-1.1.dist-info/licenses/LICENSE
inventree_zapier-1.1.dist-info/METADATA
inventree_zapier-1.1.dist-info/WHEEL
inventree_zapier-1.1.dist-info/entry_points.txt
inventree_zapier-1.1.dist-info/top_level.txt
inventree_zapier-1.1.dist-info/RECORD
